wireup/__init__.py
wireup/_annotations.py
wireup/_decorators.py
wireup/_discovery.py
wireup/errors.py
wireup/integration/__init__.py
wireup/integration/aiohttp.py
wireup/integration/click.py
wireup/integration/django/__init__.py
wireup/integration/django/apps.py
wireup/integration/django/decorators.py
wireup/integration/fastapi.py
wireup/integration/flask.py
wireup/integration/starlette.py
wireup/ioc/__init__.py
wireup/ioc/_exit_stack.py
wireup/ioc/container/__init__.py
wireup/ioc/container/async_container.py
wireup/ioc/container/base_container.py
wireup/ioc/container/sync_container.py
wireup/ioc/factory_compiler.py
wireup/ioc/override_manager.py
wireup/ioc/parameter.py
wireup/ioc/service_registry.py
wireup/ioc/type_analysis.py
wireup/ioc/types.py
wireup/ioc/util.py
wireup/py.typed
wireup-2.3.0.dist-info/METADATA
wireup-2.3.0.dist-info/WHEEL
wireup-2.3.0.dist-info/RECORD
