Metadata-Version: 2.1
Name: wireup
Version: 2.3.0
Summary: Python Dependency Injection Library
Home-page: https://github.com/maldoinc/wireup
License: MIT
Keywords: flask,django,injector,dependency injection,dependency injection container,dependency injector
Author: Aldo Mateli
Author-email: aldo.mateli@gmail.com
Requires-Python: >=3.8,<4.0
Classifier: Development Status :: 5 - Production/Stable
Classifier: Environment :: Console
Classifier: Environment :: Web Environment
Classifier: Framework :: Django
Classifier: Framework :: FastAPI
Classifier: Framework :: Flask
Classifier: Framework :: aiohttp
Classifier: Intended Audience :: Developers
Classifier: License :: OSI Approved :: MIT License
Classifier: Operating System :: OS Independent
Classifier: Programming Language :: Python
Classifier: Programming Language :: Python :: 3
Classifier: Programming Language :: Python :: 3.8
Classifier: Programming Language :: Python :: 3.9
Classifier: Programming Language :: Python :: 3.10
Classifier: Programming Language :: Python :: 3.11
Classifier: Programming Language :: Python :: 3.12
Classifier: Programming Language :: Python :: 3.13
Classifier: Programming Language :: Python :: 3 :: Only
Classifier: Programming Language :: Python :: 3.14
Classifier: Topic :: Software Development :: Libraries :: Python Modules
Classifier: Typing :: Typed
Provides-Extra: eval-type
Requires-Dist: eval-type-backport (>=0.2.0,<0.3.0) ; (python_version < "3.11") and (extra == "eval-type")
Requires-Dist: typing_extensions (>=4.7,<5.0)
Project-URL: Changelog, https://github.com/maldoinc/wireup/releases
Project-URL: Documentation, https://maldoinc.github.io/wireup/
Project-URL: Repository, https://github.com/maldoinc/wireup
